notes_seq/divM.v
module divM(input wire clk_in, output wire clk_out, output reg [3:0] out = 0);
  parameter BITS = 12_000_000;
  //-- Numero de bits para almacenar el divisor
  //-- Se calculan con la funcion de verilog $clog2, que nos devuelve el
  //-- numero de bits necesarios para representar el numero M
  //-- Es un parametro local, que no se puede modificar al instanciar
  localparam N = $clog2(BITS);

  //-- Registro para implementar el contador modulo M
  reg [N-1:0] divcounter = 0;

  //-- Modulus 3 counter
  always @(posedge clk_in) begin
    divcounter <= (divcounter == BITS - 1) ? 0 : divcounter + 1;
  end

  //Take out MSB
  assign clk_out = divcounter[N-1];

endmodule

freq_divider/divM_tb.v
`timescale 1ns / 100ps
module divM_tb;

  reg clk_in = 0;
  wire clk_out;

  divM  #(.number(2))
    uut(.clk_in(clk_in), .clk_out(clk_out));

  //Clock generator
  always #1 clk_in = ~clk_in;

  initial begin
    $dumpfile("divM_tb.vcd");
    $dumpvars;

    #30 $display("Simulation finished");
    $finish;
  end
endmodule

freq_divider/divM_tb.vcd
$date
	Tue May 10 14:59:36 2016
$end
$version
	Icarus Verilog
$end
$timescale
	100ps
$end
$scope module divM_tb $end
$var wire 1 ! clk_out $end
$var reg 1 " clk_in $end
$scope module uut $end
$var wire 1 " clk_in $end
$var wire 1 ! clk_out $end
$var reg 1 # divcounter $end
$upscope $end
$upscope $end
$enddefinitions $end
#0
$dumpvars
0#
0"
0!
$end
#10
1!
1#
1"
#20
0"
#30
0!
0#
1"
#40
0"
#50
1!
1#
1"
#60
0"
#70
0!
0#
1"
#80
0"
#90
1!
1#
1"
#100
0"
#110
0!
0#
1"
#120
0"
#130
1!
1#
1"
#140
0"
#150
0!
0#
1"
#160
0"
#170
1!
1#
1"
#180
0"
#190
0!
0#
1"
#200
0"
#210
1!
1#
1"
#220
0"
#230
0!
0#
1"
#240
0"
#250
1!
1#
1"
#260
0"
#270
0!
0#
1"
#280
0"
#290
1!
1#
1"
