2-bit-comparator/2-bit-comparator.v
module two_bit_comparator(
  input [1:0] input0,
  input [1:0] input1,
  output output0
  );

  assign output0 = (input0[0] & input1[0] & input0[1] & input1[1]) |
                    (~input0[0] & ~input1[0] & ~input0[1] & ~input1[1]) |
                    (~input0[0] & ~input1[0] & input0[1] & input1[1]) |
                    (input0[0] & input1[0] & ~input0[1] & ~input1[1]);

endmodule

2-bit-comparator/stimulus_tb.v
module two_bit_comparator_tb;
  reg[1:0] input0;
  reg[1:0] input1;

  wire outpu0;

  two_bit_comparator uut (
    .input0(input0),
    .input1(input1),
    .output0(output0)
    );

  initial begin
    $dumpfile("test.vcd");
    $dumpvars(0, two_bit_comparator_tb);

    //Initialize inputs
    input0 = 0;
    input1 = 0;
    //Current state is 0000
    #20 input0 = 1; //0100
    #20 input1 = 1; //0101
    #20 input1 = 3; //0111
    #20 input0 = 3; //1111
    #20 input1 = 1; //1101
    #20 input1 = 0; //1100
    #20 input0 = 2; //1000
    #20 input1 = 2; //1010
    #40 ;

  end

  initial begin
    $monitor("TIME=%3d:     x=%2b y=%2b z=%d \n",$time,input0,input1,output0, );
  end
endmodule

2-bit-comparator/test.vcd
$date
	Fri May  6 21:44:41 2016
$end
$version
	Icarus Verilog
$end
$timescale
	1s
$end
$scope module two_bit_comparator_tb $end
$var wire 1 ! output0 $end
$var reg 2 " input0 [1:0] $end
$var reg 2 # input1 [1:0] $end
$scope module uut $end
$var wire 2 $ input0 [1:0] $end
$var wire 2 % input1 [1:0] $end
$var wire 1 ! output0 $end
$upscope $end
$upscope $end
$enddefinitions $end
#0
$dumpvars
b0 %
b0 $
b0 #
b0 "
1!
$end
#20
0!
b1 "
b1 $
#40
1!
b1 #
b1 %
#60
0!
b11 #
b11 %
#80
1!
b11 "
b11 $
#100
0!
b1 #
b1 %
#120
b0 #
b0 %
#140
b10 "
b10 $
#160
1!
b10 #
b10 %
