adder/adder_gate.v
module adder_gate(input x, input y, input cin, output res, output cout);

  wire p, s, r;

  xor(p, x, y);
  and(s, x, y);
  and(r, p, cin);
  or(cout, r, s);
  xor(res, p, cin);

endmodule

adder/adder_gate_tb.v
`timescale 1ns / 100ps

module adder_gate_tb;

  reg input1;
  reg input2;
  reg carryin;

  wire out;
  wire carryout;

  adder_gate uut (
    .x(input1),
    .y(input2),
    .cin(carryin),
    .res(res),
    .cout(carryout)
    );

  initial begin
    $dumpfile("adder.vcd");
    $dumpvars(0,adder_gate_tb);
    input1 = 0;
    input2 = 0;
    carryin = 0;

    #20  input1 = 1;
    #20; input2 = 1;
    #20; input1 = 0;
    #20; carryin = 1;
    #20; input2 = 0;
    #20; input1 = 1;
    #20; input2 = 1;
    #40;
  end

  initial begin
    $monitor("time = %2d, CIN =%1b, IN1=%1b, IN2=%1b, COUT=%1b, OUT_A=%1b", $time,carryin,input2, input1,carryout,res);
  end
endmodule

adder/adder.vcd
$date
	Fri May  6 23:41:24 2016
$end
$version
	Icarus Verilog
$end
$timescale
	100ps
$end
$scope module adder_gate_tb $end
$var wire 1 ! res $end
$var wire 1 " carryout $end
$var reg 1 # carryin $end
$var reg 1 $ input1 $end
$var reg 1 % input2 $end
$scope module uut $end
$var wire 1 # cin $end
$var wire 1 " cout $end
$var wire 1 & p $end
$var wire 1 ' r $end
$var wire 1 ! res $end
$var wire 1 ( s $end
$var wire 1 $ x $end
$var wire 1 % y $end
$upscope $end
$upscope $end
$enddefinitions $end
#0
$dumpvars
0(
0'
0&
0%
0$
0#
0"
0!
$end
#200
1!
1&
1$
#400
0!
1"
0&
1(
1%
#600
1!
0"
1&
0(
0$
#800
1"
1'
0!
1#
#1000
0"
0'
1!
0&
0%
#1200
1"
1'
0!
1&
1$
#1400
0'
1!
0&
1(
1%
