adder/adder_udp.v
module adder_udp(input x, input y, input cin, output res, output cout);

  addresult(res, cin, x, y);
  addcarry(cout, cin, x, y);

endmodule


primitive addresult(res, cin, x, y);
  output res;
  input cin,x,y;

  table
  //cin x   y   res
    0   0   0 : 0 ;
    0   0   1 : 1 ;
    0   1   0 : 1 ;
    0   1   1 : 0 ;
    1   0   0 : 1 ;
    1   0   1 : 0 ;
    1   1   0 : 0 ;
    1   1   1 : 1 ;
  endtable
endprimitive

primitive addcarry(cout, cin, x, y);
  output cout;
  input cin, x, y;

  table
  //cin   x   y : cout
    0     0   0 : 0 ;
    0     0   1 : 0 ;
    0     1   0 : 0 ;
    0     1   1 : 1 ;
    1     0   0 : 0 ;
    1     0   1 : 1 ;
    1     1   0 : 1 ;
    1     1   1 : 1 ;
  endtable
endprimitive

adder/adder_udp_tb.v
`timescale 1ns / 100ps

module adder_udp_tb;

  reg x;
  reg y;
  reg cin;

  wire res;
  wire cout;

  adder_udp uut (
    .x(x),
    .y(y),
    .cin(cin),
    .res(res),
    .cout(cout)
    );

  initial begin
    $dumpfile("adder_udp.vcd");
    $dumpvars(0, adder_udp_tb);
    x = 0;
    y = 0;
    cin = 0;

    #20  x = 1;
    #20; y = 1;
    #20; x = 0;
    #20; cin = 1;
    #20; y = 0;
    #20; x = 1;
    #20; y = 1;
    #40;
  end

  initial begin
    $monitor("time = %2d, CIN =%1b, X=%1b, Y=%1b, COUT=%1b, RES=%1b", $time, cin, y, x, cout, res);
  end
endmodule

adder/adder_udp.vcd
$date
	Fri May  6 23:42:00 2016
$end
$version
	Icarus Verilog
$end
$timescale
	100ps
$end
$scope module adder_udp_tb $end
$var wire 1 ! res $end
$var wire 1 " cout $end
$var reg 1 # cin $end
$var reg 1 $ x $end
$var reg 1 % y $end
$scope module uut $end
$var wire 1 # cin $end
$var wire 1 " cout $end
$var wire 1 ! res $end
$var wire 1 $ x $end
$var wire 1 % y $end
$upscope $end
$upscope $end
$enddefinitions $end
#0
$dumpvars
0%
0$
0#
0"
0!
$end
#200
1!
1$
#400
0!
1"
1%
#600
1!
0"
0$
#800
0!
1"
1#
#1000
1!
0"
0%
#1200
0!
1"
1$
#1400
1!
1%
