ram_mem/src/ram_mem.v
module ram_mem(
  input wire clk,
  input wire [3:0] address,
  input wire mode,
  input wire [3:0] data,
  output reg [3:0] out
  );

  reg [3:0] ram [0:15];

  initial begin
    ram[0] = 4'd0;
    ram[1] = 4'd1;
    ram[2] = 4'd2;
    ram[3] = 4'd3;
    ram[4] = 4'd4;
    ram[5] = 4'd5;
    ram[6] = 4'd6;
    ram[7] = 4'd7;
    ram[8] = 4'd8;
    ram[9] = 4'd9;
    ram[10] = 4'd10;
    ram[11] = 4'd11;
    ram[12] = 4'd12;
    ram[13] = 4'd13;
    ram[14] = 4'd14;
    ram[15] = 4'd15;
  end

  always @ ( posedge clk ) begin
    if(mode == 0) begin   //Read
      out <= ram[address];
    end
  end

  always @ ( posedge clk ) begin
    if (mode == 1) begin   //Write
      ram[address] <= data;
      out <= 0;
    end
  end

endmodule

ram_mem/src/ram_mem_tb.v
module ram_mem_tb;

  reg clk = 0;
  reg [3:0] address = 4'd0;
  reg [3:0] data;
  reg mode;
  wire [3:0] out;

  ram_mem uut(.clk(clk), .address(address), .data(data), .mode(mode), .out(out));

  always #1 clk = !clk;

  initial begin
    $dumpfile("ram_mem_tb.vcd");
    $dumpvars;

    $monitor($time, ": clk=%b data=%b address=%b mode=%b out=%d", clk, data, address, mode, out);

    #1 mode=0; data=4'b0; address=0;
    #1 mode=0; data=4'b0; address=1;
    #1 mode=0; data=4'b0; address=2;
    #1 mode=0; data=4'b0; address=5;
    #1 mode=0; data=4'b0; address=10;
    #1 mode=0; data=4'b0; address=12;
    #1 mode=0; data=4'b0; address=15;
    #2 mode=1;
    data=4'd9; address=0;
    #2 mode=0;
    data=4'b0; address=0;
    #2 mode=1;
    data=4'd11; address=0;
    #2 mode=0;
    data=4'b0; address=0;
    #2 mode=0;
    data=4'b0; address=0;
    #2 mode=1;
    data=4'd13; address=0;
    #2 mode=0;
    data=4'b0; address=0;

    $finish;
  end

endmodule

ram_mem/src/ram_mem_tb.vcd
$date
	Fri May 20 22:34:43 2016
$end
$version
	Icarus Verilog
$end
$timescale
	1s
$end
$scope module ram_mem_tb $end
$var wire 4 ! out [3:0] $end
$var reg 4 " address [3:0] $end
$var reg 1 # clk $end
$var reg 4 $ data [3:0] $end
$var reg 1 % mode $end
$scope module uut $end
$var wire 4 & address [3:0] $end
$var wire 1 # clk $end
$var wire 4 ' data [3:0] $end
$var wire 1 % mode $end
$var reg 4 ( out [3:0] $end
$upscope $end
$upscope $end
$enddefinitions $end
#0
$dumpvars
bx (
bx '
b0 &
x%
bx $
0#
b0 "
bx !
$end
#1
b0 !
b0 (
b0 $
b0 '
0%
1#
#2
b1 "
b1 &
0#
#3
b10 !
b10 (
b10 "
b10 &
1#
#4
b101 "
b101 &
0#
#5
b1010 !
b1010 (
b1010 "
b1010 &
1#
#6
b1100 "
b1100 &
0#
#7
b1111 !
b1111 (
b1111 "
b1111 &
1#
#8
0#
#9
b0 !
b0 (
1#
b0 "
b0 &
b1001 $
b1001 '
1%
#10
0#
#11
b1001 !
b1001 (
1#
b0 $
b0 '
0%
#12
0#
#13
b0 !
b0 (
1#
b1011 $
b1011 '
1%
#14
0#
#15
b1011 !
b1011 (
1#
b0 $
b0 '
0%
#16
0#
#17
1#
#18
0#
#19
b0 !
b0 (
1#
b1101 $
b1101 '
1%
#20
0#
#21
b1101 !
b1101 (
1#
b0 $
b0 '
0%
